superq/__init__.py
superq/backends/__init__.py
superq/backends/backend_base.py
superq/backends/backend_mongo.py
superq/backends/backend_sqlite.py
superq/bson.py
superq/callbacks.py
superq/cli.py
superq/config.py
superq/exceptions.py
superq/executors/__init__.py
superq/executors/executor_asyncio.py
superq/executors/executor_base.py
superq/executors/executor_pool.py
superq/executors/executor_process.py
superq/executors/executor_thread.py
superq/queues.py
superq/tasks.py
superq/tests/__init__.py
superq/tests/conftest.py
superq/tests/test_cli.py
superq/tests/test_executors.py
superq/tests/test_helpers.py
superq/tests/test_tasks.py
superq/workers.py
superq/wrapped_fn.py
superq-0.2.1.dist-info/LICENSE
superq-0.2.1.dist-info/METADATA
superq-0.2.1.dist-info/WHEEL
superq-0.2.1.dist-info/entry_points.txt
superq-0.2.1.dist-info/RECORD
